{"stat.walkOneCm":65627,"stat.leaveGame":7,"stat.mineBlock.minecraft.sandstone":1,"stat.flyOneCm":100992,"stat.jump":308,"stat.swimOneCm":2443,"stat.playOneMinute":53261,"stat.fallOneCm":39403,"stat.climbOneCm":214,"stat.useItem.minecraft.stone_pickaxe":1,"stat.damageDealt":655,"stat.crouchOneCm":881,"stat.timeSinceDeath":53261,"stat.sprintOneCm":45491,"achievement.exploreAllBiomes":{"value":0,"progress":["Forest","Plains","Swampland"]},"stat.diveOneCm":386,"stat.useItem.minecraft.sandstone":50}